pyalert/__init__.py
pyalert/pyalert.py
pyalert_gmail-0.1.1.dist-info/licenses/LICENSE
pyalert_gmail-0.1.1.dist-info/METADATA
pyalert_gmail-0.1.1.dist-info/WHEEL
pyalert_gmail-0.1.1.dist-info/top_level.txt
pyalert_gmail-0.1.1.dist-info/RECORD
