Metadata-Version: 2.4
Name: pyalert-gmail
Version: 0.1.1
Summary: A Python package for sending email notifications using the Gmail API.
Home-page: https://github.com/MisterSoandSo/pyalert
Author: MisterSoandSo
Author-email: asoso221@gmail.com
Classifier: Programming Language :: Python :: 3
Classifier: License :: OSI Approved :: MIT License
Classifier: Operating System :: OS Independent
Requires-Python: >=3.6
License-File: LICENSE
Requires-Dist: google-api-python-client>=2.165.0
Requires-Dist: google-auth>=2.38.0
Requires-Dist: google-auth-httplib2>=0.2.0
Requires-Dist: google-auth-oauthlib>=1.2.1
Requires-Dist: requests>=2.32.3
Requires-Dist: requests-oauthlib>=2.0.0
Dynamic: author
Dynamic: author-email
Dynamic: classifier
Dynamic: description
Dynamic: description-content-type
Dynamic: home-page
Dynamic: license-file
Dynamic: requires-dist
Dynamic: requires-python
Dynamic: summary
